pedlar/__init__.py
pedlar/agent.py
pedlar/basic.py
pedlar/echo.py
pedlar/interactive.py
pedlar/utils.py
pedlar-0.0.8.dist-info/LICENSE
pedlar-0.0.8.dist-info/METADATA
pedlar-0.0.8.dist-info/WHEEL
pedlar-0.0.8.dist-info/top_level.txt
pedlar-0.0.8.dist-info/RECORD
