Metadata-Version: 2.1
Name: pedlar
Version: 0.0.8
Summary: Algorithmic Trading Platform for Python
Home-page: https://github.com/nuric/pedlar
Author: nuric
Author-email: nuric@users.noreply.github.com
License: UNKNOWN
Platform: UNKNOWN
Classifier: Development Status :: 3 - Alpha
Classifier: License :: OSI Approved :: Apache Software License
Classifier: Natural Language :: English
Classifier: Operating System :: OS Independent
Classifier: Programming Language :: Python :: 3 :: Only
Classifier: Topic :: Office/Business :: Financial
Requires-Dist: pyzmq
Requires-Dist: requests
